[{"slot_tier":"Head","item":" Thraexhelm of the Onyx Crucible","source":"Catalyst\nRaszageth / Magmorax / Tindral Sageswift","itemid":"217218","item_link":"https://www.wowhead.com/item=217218/thraexhelm-of-the-onyx-crucible?bonus=7981:10358:5871","source_link":"https://www.wowhead.com/npc=210601/tindral-sageswift"},{"slot_tier":"Neck","item":" Ouroboreal Necklet","source":"Volcoross","itemid":"210214","item_link":"https://www.wowhead.com/item=210214/ouroboreal-necklet?bonus=7981:10358:5871","source_link":"https://www.wowhead.com/npc=208478/volcoross"},{"slot_tier":"Shoulders","item":" Pauldrons of the Onyx Crucible","source":"Catalyst\nBroodkeeper Diurna / Neltharion / Smolderon","itemid":"217220","item_link":"https://www.wowhead.com/item=217220/pauldrons-of-the-onyx-crucible?bonus=7981:10358:5871","source_link":"https://www.wowhead.com/npc=200927/smolderon"},{"slot_tier":"Cloak","item":" Vibrant Wildercloth Shawl","source":"Crafting","itemid":"193511","item_link":"https://www.wowhead.com/item=193511/vibrant-wildercloth-shawl?bonus=10249:1509"},{"slot_tier":"Chest","item":" Battlechest of the Onyx Crucible","source":"Catalyst\nKurog Grimtotem / Zskarn / Nymue","itemid":"217216","item_link":"https://www.wowhead.com/item=217216/battlechest-of-the-onyx-crucible?bonus=7981:10358:5871","source_link":"https://www.wowhead.com/npc=206172/nymue"},{"slot_tier":"Wrist","item":" Primal Molten Vambraces","source":"Crafting","itemid":"190502","item_link":"https://www.wowhead.com/item=190502/primal-molten-vambraces?bonus=10249:1509"},{"slot_tier":"Gloves","item":" Handguards of the Onyx Crucible","source":"Catalyst\nDathea, Ascended / Neldris / Igira the Cruel","itemid":"217217","item_link":"https://www.wowhead.com/item=217217/handguards-of-the-onyx-crucible?bonus=7981:10358:5871","source_link":"https://www.wowhead.com/npc=206689/igira-the-cruel"},{"slot_tier":"Belt","item":" Seal of the Defiant Hordes","source":"Warlord Kagni","itemid":"202577","item_link":"https://www.wowhead.com/item=202577/seal-of-the-defiant-hordes?bonus=7981:10358:5871","source_link":"https://www.wowhead.com/npc=199659/warlord-kagni"},{"slot_tier":"Legs","item":" Legplates of the Onyx Crucible","source":"Catalyst\nSennarth / Rashok / Larodar, Keeper of the Flame","itemid":"217219","item_link":"https://www.wowhead.com/item=217219/legplates-of-the-onyx-crucible?bonus=7981:10358:5871","source_link":"https://www.wowhead.com/npc=208445/larodar-keeper-of-the-flame"},{"slot_tier":"Boots","item":" Fused Obsidian Sabatons","source":"Smolderon","itemid":"207156","item_link":"https://www.wowhead.com/item=207156/fused-obsidian-sabatons?bonus=7981:10358:5871","source_link":"https://www.wowhead.com/npc=200927/smolderon"},{"slot_tier":"Ring","item":" Seal of Diurna's Chosen","source":"Eranog","itemid":"195480","item_link":"https://www.wowhead.com/item=195480/seal-of-diurnas-chosen?bonus=7981:10358:5871","source_link":"https://www.wowhead.com/npc=184972/eranog"},{"slot_tier":"Ring","item":" Seal of Filial Duty","source":"Broodkeeper Diurna","itemid":"195526","item_link":"https://www.wowhead.com/item=195526/seal-of-filial-duty?bonus=7981:10358:5878","source_link":"https://www.wowhead.com/npc=190245/broodkeeper-diurna"},{"slot_tier":"Trinket (Offensive)","item":" Cataclysmic Signet Brand","source":"Smolderon","itemid":"207166","item_link":"https://www.wowhead.com/item=207166/cataclysmic-signet-brand?bonus=7981:10358:5871","source_link":"https://www.wowhead.com/npc=200927/smolderon"},{"slot_tier":"Trinket (Offensive)","item":" Elementium Pocket Anvil","source":"Essence of Shadow","itemid":"202617","item_link":"https://www.wowhead.com/item=202617/elementium-pocket-anvil?bonus=7981:10358:5871","source_link":"https://www.wowhead.com/npc=201774/essence-of-shadow"},{"slot_tier":"Trinket (Defensive)","item":" Treemouth's Festering Splinter","source":"Brackenhide Hollow","itemid":"193652","item_link":"https://www.wowhead.com/item=193652/treemouths-festering-splinter?bonus=657:10358:5871:7981","source_link":"https://www.wowhead.com/zone=13991/brackenhide-hollow"},{"slot_tier":"Trinket (Defensive)","item":" Fyrakk's Tainted Rageheart","source":"Fyrakk","itemid":"207174","item_link":"https://www.wowhead.com/item=207174/fyrakks-tainted-rageheart?bonus=7981:10358:5878","source_link":"https://www.wowhead.com/npc=213646/fyrakk"},{"slot_tier":"Weapon","item":" Gholak, the Final Conflagration","source":"Fyrakk","itemid":"207786","item_link":"https://www.wowhead.com/item=207786/gholak-the-final-conflagration?bonus=7981:10358:5871","source_link":"https://www.wowhead.com/npc=204931/fyrakk"},{"slot_tier":"Shield","item":" Verdant Matrix Beacon","source":"Nymue","itemid":"207798","item_link":"https://www.wowhead.com/item=207798/verdant-matrix-beacon?bonus=7981:10358:5871","source_link":"https://www.wowhead.com/npc=206172/nymue"},{"slot_tier":"Trinket (Defensive)","item":" Enduring Dreadplate","source":"Kazzara, the Hellforged","itemid":"202616","item_link":"https://www.wowhead.com/item=202616/enduring-dreadplate?bonus=7981:10358:5871","source_link":"https://www.wowhead.com/npc=201261/kazzara-the-hellforged"},{"slot_tier":"Neck","item":" Tuskarr Bone Necklace","source":"Brackenhide Hollow","itemid":"193666","item_link":"https://www.wowhead.com/item=193666/tuskarr-bone-necklace?bonus=657:10358:5871:7981","source_link":"https://www.wowhead.com/zone=13991/brackenhide-hollow"},{"slot_tier":"Belt","item":" Trapmaster's Utility Belt","source":"Brackenhide Hollow","itemid":"193669","item_link":"https://www.wowhead.com/item=193669/trapmasters-utility-belt?bonus=657:10358:5871:7981","source_link":"https://www.wowhead.com/zone=13991/brackenhide-hollow"},{"slot_tier":"Boots","item":" Pristine Magma Stompers","source":"Neltharus","itemid":"193771","item_link":"https://www.wowhead.com/item=193771/pristine-magma-stompers?bonus=657:10358:5871:7981","source_link":"https://www.wowhead.com/zone=14011/neltharus"},{"slot_tier":"Ring","item":" Unstable Arcane Loop","source":"The Azure Vault","itemid":"193633","item_link":"https://www.wowhead.com/item=193633/unstable-arcane-loop?bonus=657:10358:5871:7981","source_link":"https://www.wowhead.com/zone=13954/the-azure-vault"},{"slot_tier":"Ring","item":" Eternal Sentry's Ring","source":"Uldaman","itemid":"193804","item_link":"https://www.wowhead.com/item=193804/eternal-sentrys-ring?bonus=657:10358:5871:7981","source_link":"https://www.wowhead.com/zone=13968/uldaman"},{"slot_tier":"Trinket(Offensive)","item":" Blazebinder's Hoof","source":"Ruby Life Pools","itemid":"193762","item_link":"https://www.wowhead.com/item=193762/blazebinders-hoof?bonus=657:10358:5871:7981","source_link":"https://www.wowhead.com/zone=14063/ruby-life-pools"},{"slot_tier":"Trinket(Offensive)","item":" Idol of Trampling Hooves","source":"The Nokhud Offensive","itemid":"193679","item_link":"https://www.wowhead.com/item=193679/idol-of-trampling-hooves?bonus=657:10358:5871:7981","source_link":"https://www.wowhead.com/zone=13982/the-nokhud-offensive"},{"slot_tier":"Weapon","item":" Strike Twice","source":"The Nokhud Offensive","itemid":"193700","item_link":"https://www.wowhead.com/item=193700/strike-twice?bonus=657:10358:5871:7981","source_link":"https://www.wowhead.com/zone=13982/the-nokhud-offensive"},{"slot_tier":"Shield","item":" Crystalized Bulwark","source":"The Azure Vault","itemid":"193645","item_link":"https://www.wowhead.com/item=193645/crystalized-bulwark?bonus=657:10358:5871:7981","source_link":"https://www.wowhead.com/zone=13954/the-azure-vault"},{"slot_tier":"Grade","item":"Trinket","source":"Drop Location"},{"slot_tier":"S+","item":" Manic Grieftorch","source":"Broodkeeper Diurna","itemid":"194308","item_link":"https://www.wowhead.com/item=194308/manic-grieftorch?bonus=7981:10358:5871","source_link":"https://www.wowhead.com/npc=190245/broodkeeper-diurna"},{"slot_tier":"A+","item":" All-Totem of the Master","source":"Kurog Grimtotem","itemid":"194306","item_link":"https://www.wowhead.com/item=194306/all-totem-of-the-master?bonus=7981:10358:5871","source_link":"https://www.wowhead.com/npc=181378/kurog-grimtotem"},{"slot_tier":"A+","item":" Gift of Ursine Vengeance","source":"Council of Dreams","itemid":"207173","item_link":"https://www.wowhead.com/item=207173/gift-of-ursine-vengeance?bonus=7981:10358:5871","source_link":"https://www.wowhead.com/npc=208363"},{"slot_tier":"A","item":" Augury of the Primal Flame","source":"Fyrakk","itemid":"208614","item_link":"https://www.wowhead.com/item=208614/augury-of-the-primal-flame?bonus=7981:10358:5871","source_link":"https://www.wowhead.com/npc=204931/fyrakk"},{"slot_tier":"B+","item":" Branch of the Tormented Ancient","source":"Gnarlroot","itemid":"202613","item_link":"https://www.wowhead.com/item=202613/zaqali-chaos-grapnel?bonus=7981:10358:5871","source_link":"https://www.wowhead.com/npc=209333/gnarlroot"},{"slot_tier":"B","item":" Whispering Incarnate Icon","source":"Primal Council","itemid":"194301","item_link":"https://www.wowhead.com/item=194301/whispering-incarnate-icon?bonus=7981:10358:5871","source_link":"https://www.wowhead.com/npc=187771"},{"slot_tier":"B","item":" Spiteful Storm","source":"Raszageth","itemid":"194309","item_link":"https://www.wowhead.com/item=194309/spiteful-storm?bonus=7981:10358:5871","source_link":"https://www.wowhead.com/npc=189492/raszageth"},{"slot_tier":"B","item":" Beacon to the Beyond","source":"Sarkareth","itemid":"203963","item_link":"https://www.wowhead.com/item=203963/beacon-to-the-beyond?bonus=7981:10358:5871","source_link":"https://www.wowhead.com/npc=201754/sarkareth"},{"slot_tier":"C","item":" Granyth's Enduring Scale","source":"The Nokhud Offensive","itemid":"193689","item_link":"https://www.wowhead.com/item=193689/granyths-enduring-scale?bonus=657:10358:5871:7981","source_link":"https://www.wowhead.com/zone=13982/the-nokhud-offensive"}]